nonebot_plugin_openai/__init__.py
nonebot_plugin_openai-0.0.3.dist-info/METADATA
nonebot_plugin_openai-0.0.3.dist-info/WHEEL
nonebot_plugin_openai-0.0.3.dist-info/top_level.txt
nonebot_plugin_openai-0.0.3.dist-info/RECORD
