Metadata-Version: 2.1
Name: nonebot-plugin-openai
Version: 0.0.3
Summary: A plugin for nonebot to chat
Home-page: https://github.com/InariInDream/nonebot_plugin_openai
Author: InariInDream
Author-email: inariindream@163.com
Classifier: Programming Language :: Python :: 3
Classifier: License :: OSI Approved :: MIT License
Classifier: Operating System :: OS Independent
Requires-Dist: openai (>=0.25.0)
Requires-Dist: nonebot-plugin-apscheduler (>=0.1.3)
Requires-Dist: nonebot-adapter-onebot (>=2.0.0-beta.1)
Requires-Dist: nonebot2 (>=2.0.0-beta.4)
